{"sdg_goal":"4","indicator_number":4.6,"graph_title":"global_indicators.4-6-title","indicator_sort_order":"04-06-01","data_non_statistical":false,"graph_type":"line","computation_units":"Prozent","data_start_values":[{"field":"Region","value":"Enzkreis"},{"field":"Region","value":"Land BW"}],"national_geographical_coverage":"Land BW","computation_definitions":null,"SOURCE_TYPE":"Bertelsmann Stiftung / Wegweiser Kommune","source_earliest_available_1":null,"source_periodicity_1":null,"language":"de","published":true,"reporting_status":"complete","page_content":"Der Begriff Familienwanderung beschreibt die Migration mit dem Motiv des Wohnstandortwechsels von Familien mit ihren Kindern. Dieses Wanderungsmotiv wird \u00fcblicherweise von den 30- bis unter 50-J\u00e4hrigen, gemeinsam mit der Kindergeneration, also den unter 18-J\u00e4hrigen dominiert. Wanderungsgewinne in diesen Altersgruppen verzeichnen oftmals Regionen mit attraktiven Wohnstandorten, wie es in Baden-W\u00fcrttemberg z.B. im Umland der Oberzentren der Fall ist, so auch im Enzkreis. Eine gute verkehrliche Anbindung, die Pendlerdistanz zu den Oberzentren Stuttgart, Pforzheim und Karlsruhe und die attraktiven naturr\u00e4umlichen Besonderheiten wirken hier positiv auf den Wanderungssaldo. Die Wanderungsverluste in diesen Alterskohorten treten dagegen \u00fcberwiegend in den Regionen mit tendenziell h\u00f6heren Wohnkosten auf, wie es in der Regel in den urbanen Oberzentren der Fall ist. Ein positiver Wanderungssaldo in dieser Kohorte dr\u00fcckt die insgesamt positive Wohn- und Lebensqualit\u00e4t in \u00fcberwiegend weniger verdichteten R\u00e4umen aus. <br>\n<br>\n**ENTWICKLUNG** <br>\n<br>\nDie produktive Wirtschaftsstruktur und insgesamt hohe Lebensqualit\u00e4t im Land Baden-W\u00fcrttemberg wird u.a. durch den positiven Saldo der Familienwanderungen deutlich. Auf der kommunale Ebene zeigt sich jedoch, in Abh\u00e4ngigkeit der strukturellen Ausgangslage, ein differenziertes Bild. W\u00e4hrend die strukturstarken Oberzentren hohe Wanderungsverluste in der Gruppe der 30- bis unter 50-J\u00e4hrigen und der Kindergeneration verzeichnen, profitieren die Umlandregionen von Wanderungsgewinnen. Der Wanderungssaldo in den Kohorten der Familienwanderer ist im Enzkreis \u00fcber den gesamten Betrachtungszeitraum deutlich positiv, was weitreichende Auswirkungen auf die Altersstruktur der Bev\u00f6lkerung hat. Die Migrationsstr\u00f6me tragen wesentlich zur Verj\u00fcngung der heutigen und zuk\u00fcnftigen Bev\u00f6lkerung im Enzkreis bei, was jedoch ma\u00dfgeblich von der Verf\u00fcgbarkeit von Wohnraum abh\u00e4ngig ist.\n","national_metadata_updated_date":"2023-03-17","national_data_updated_date":"2023-03-17","target_number":"4.6","goal_number":"4","indicator_name":"global_indicators.4-6-title"}